README
setup.py
Bcfg2.egg-info/PKG-INFO
Bcfg2.egg-info/SOURCES.txt
Bcfg2.egg-info/dependency_links.txt
Bcfg2.egg-info/requires.txt
Bcfg2.egg-info/top_level.txt
src/lib/Bcfg2Py3k.py
src/lib/Component.py
src/lib/Logger.py
src/lib/Options.py
src/lib/Proxy.py
src/lib/SSLServer.py
src/lib/Statistics.py
src/lib/__init__.py
src/lib/Client/Frame.py
src/lib/Client/XML.py
src/lib/Client/__init__.py
src/lib/Client/Tools/APK.py
src/lib/Client/Tools/APT.py
src/lib/Client/Tools/Action.py
src/lib/Client/Tools/Blast.py
src/lib/Client/Tools/Chkconfig.py
src/lib/Client/Tools/DebInit.py
src/lib/Client/Tools/Encap.py
src/lib/Client/Tools/FreeBSDInit.py
src/lib/Client/Tools/FreeBSDPackage.py
src/lib/Client/Tools/IPS.py
src/lib/Client/Tools/MacPorts.py
src/lib/Client/Tools/POSIX.py
src/lib/Client/Tools/Pacman.py
src/lib/Client/Tools/Portage.py
src/lib/Client/Tools/RPMng.py
src/lib/Client/Tools/RcUpdate.py
src/lib/Client/Tools/SMF.py
src/lib/Client/Tools/SYSV.py
src/lib/Client/Tools/Systemd.py
src/lib/Client/Tools/Upstart.py
src/lib/Client/Tools/VCS.py
src/lib/Client/Tools/YUM24.py
src/lib/Client/Tools/YUMng.py
src/lib/Client/Tools/__init__.py
src/lib/Client/Tools/launchd.py
src/lib/Client/Tools/rpmtools.py
src/lib/Server/Core.py
src/lib/Server/FileMonitor.py
src/lib/Server/Plugin.py
src/lib/Server/__init__.py
src/lib/Server/Admin/Backup.py
src/lib/Server/Admin/Bundle.py
src/lib/Server/Admin/Client.py
src/lib/Server/Admin/Compare.py
src/lib/Server/Admin/Group.py
src/lib/Server/Admin/Init.py
src/lib/Server/Admin/Minestruct.py
src/lib/Server/Admin/Perf.py
src/lib/Server/Admin/Pull.py
src/lib/Server/Admin/Query.py
src/lib/Server/Admin/Reports.py
src/lib/Server/Admin/Snapshots.py
src/lib/Server/Admin/Tidy.py
src/lib/Server/Admin/Viz.py
src/lib/Server/Admin/Xcmd.py
src/lib/Server/Admin/__init__.py
src/lib/Server/Hostbase/__init__.py
src/lib/Server/Hostbase/backends.py
src/lib/Server/Hostbase/ldapauth.py
src/lib/Server/Hostbase/manage.py
src/lib/Server/Hostbase/nisauth.py
src/lib/Server/Hostbase/regex.py
src/lib/Server/Hostbase/settings.py
src/lib/Server/Hostbase/urls.py
src/lib/Server/Hostbase/hostbase/__init__.py
