Metadata-Version: 1.0
Name: Bcfg2
Version: 1.2.4
Summary: Bcfg2 Server
Home-page: UNKNOWN
Author: Narayan Desai
Author-email: desai@mcs.anl.gov
License: UNKNOWN
Platform: UNKNOWN
